Workbook

Sheet Overview
A1: Income Statement | C1: Jan | D1: Feb | E1: Mar | G1: Apr | H1: May | I1: Jun | K1: Jul | L1: Aug | M1: Sep | O1: Oct | P1: Nov | Q1: Dec | S1: Total
A3: Revenue | C3: =SUM(C4:C6) -> 24785 | D3: =SUM(D4:D6) -> 24785 | E3: =SUM(E4:E6) -> 24785 | G3: =SUM(G4:G6) -> 24785 | H3: =SUM(H4:H6) -> 24785 | I3: =SUM(I4:I6) -> 24785 | K3: =SUM(K4:K6) -> 24785 | L3: =SUM(L4:L6) -> 24785 | M3: =SUM(M4:M6) -> 24785 | O3: =SUM(O4:O6) -> 24785 | P3: =SUM(P4:P6) -> 24785 | Q3: =SUM(Q4:Q6) -> 24785 | S3: =SUM(C3:Q3) -> 297420
A4: Credit Cards | C4: =Revenue!C3 -> 23250 | D4: =Revenue!D3 -> 23250 | E4: =Revenue!E3 -> 23250 | G4: =Revenue!G3 -> 23250 | H4: =Revenue!H3 -> 23250 | I4: =Revenue!I3 -> 23250 | K4: =Revenue!K3 -> 23250 | L4: =Revenue!L3 -> 23250 | M4: =Revenue!M3 -> 23250 | O4: =Revenue!O3 -> 23250 | P4: =Revenue!P3 -> 23250 | Q4: =Revenue!Q3 -> 23250 | S4: =SUM(C4:Q4) -> 279000
A5: Checks | C5: =Revenue!C9 -> 1485 | D5: =Revenue!D9 -> 1485 | E5: =Revenue!E9 -> 1485 | G5: =Revenue!G9 -> 1485 | H5: =Revenue!H9 -> 1485 | I5: =Revenue!I9 -> 1485 | K5: =Revenue!K9 -> 1485 | L5: =Revenue!L9 -> 1485 | M5: =Revenue!M9 -> 1485 | O5: =Revenue!O9 -> 1485 | P5: =Revenue!P9 -> 1485 | Q5: =Revenue!Q9 -> 1485 | S5: =SUM(C5:Q5) -> 17820
A6: Other | C6: =Revenue!C13 -> 50 | D6: =Revenue!D13 -> 50 | E6: =Revenue!E13 -> 50 | G6: =Revenue!G13 -> 50 | H6: =Revenue!H13 -> 50 | I6: =Revenue!I13 -> 50 | K6: =Revenue!K13 -> 50 | L6: =Revenue!L13 -> 50 | M6: =Revenue!M13 -> 50 | O6: =Revenue!O13 -> 50 | P6: =Revenue!P13 -> 50 | Q6: =Revenue!Q13 -> 50 | S6: =SUM(C6:Q6) -> 600
A8: COGS | C8: =COGS!B15 -> 6050 | D8: =COGS!C15 -> 6050 | E8: =COGS!D15 -> 6050 | G8: =COGS!F15 -> 6050 | H8: =COGS!G15 -> 6050 | I8: =COGS!H15 -> 6050 | K8: =COGS!J15 -> 6050 | L8: =COGS!K15 -> 6050 | M8: =COGS!L15 -> 6050 | O8: =COGS!N15 -> 6050 | P8: =COGS!O15 -> 6050 | Q8: =COGS!P15 -> 6050 | S8: =SUM(C8:Q8) -> 72600
A10: Marketing | C10: =SUM(C11:C13) -> 1120 | D10: =SUM(D11:D13) -> 1120 | E10: =SUM(E11:E13) -> 1120 | G10: =SUM(G11:G13) -> 1120 | H10: =SUM(H11:H13) -> 1120 | I10: =SUM(I11:I13) -> 1120 | K10: =SUM(K11:K13) -> 1120 | L10: =SUM(L11:L13) -> 1120 | M10: =SUM(M11:M13) -> 1120 | O10: =SUM(O11:O13) -> 1120 | P10: =SUM(P11:P13) -> 1120 | Q10: =SUM(Q11:Q13) -> 1120 | S10: =SUM(C10:Q10) -> 13440
A11: Online Channels | C11: =Marketing!B3 -> 1000 | D11: =Marketing!C3 -> 1000 | E11: =Marketing!D3 -> 1000 | G11: =Marketing!F3 -> 1000 | H11: =Marketing!G3 -> 1000 | I11: =Marketing!H3 -> 1000 | K11: =Marketing!J3 -> 1000 | L11: =Marketing!K3 -> 1000 | M11: =Marketing!L3 -> 1000 | O11: =Marketing!N3 -> 1000 | P11: =Marketing!O3 -> 1000 | Q11: =Marketing!P3 -> 1000 | S11: =SUM(C11:Q11) -> 12000
A12: Offline Channels | C12: =Marketing!B7 -> 110 | D12: =Marketing!C7 -> 110 | E12: =Marketing!D7 -> 110 | G12: =Marketing!F7 -> 110 | H12: =Marketing!G7 -> 110 | I12: =Marketing!H7 -> 110 | K12: =Marketing!J7 -> 110 | L12: =Marketing!K7 -> 110 | M12: =Marketing!L7 -> 110 | O12: =Marketing!N7 -> 110 | P12: =Marketing!O7 -> 110 | Q12: =Marketing!P7 -> 110 | S12: =SUM(C12:Q12) -> 1320
A13: Other | C13: =Marketing!B12 -> 10 | D13: =Marketing!C12 -> 10 | E13: =Marketing!D12 -> 10 | G13: =Marketing!F12 -> 10 | H13: =Marketing!G12 -> 10 | I13: =Marketing!H12 -> 10 | K13: =Marketing!J12 -> 10 | L13: =Marketing!K12 -> 10 | M13: =Marketing!L12 -> 10 | O13: =Marketing!N12 -> 10 | P13: =Marketing!O12 -> 10 | Q13: =Marketing!P12 -> 10 | S13: =SUM(C13:Q13) -> 120
A15: Payroll & Staffing | C15: =SUM(C16:C19) -> 16050 | D15: =SUM(D16:D19) -> 16050 | E15: =SUM(E16:E19) -> 16050 | G15: =SUM(G16:G19) -> 16050 | H15: =SUM(H16:H19) -> 16050 | I15: =SUM(I16:I19) -> 16050 | K15: =SUM(K16:K19) -> 16050 | L15: =SUM(L16:L19) -> 16050 | M15: =SUM(M16:M19) -> 16050 | O15: =SUM(O16:O19) -> 16050 | P15: =SUM(P16:P19) -> 16050 | Q15: =SUM(Q16:Q19) -> 16050 | S15: =SUM(C15:Q15) -> 192600
A16: W2 Staff | C16: =Staffing!B3 -> 13000 | D16: =Staffing!C3 -> 13000 | E16: =Staffing!D3 -> 13000 | G16: =Staffing!F3 -> 13000 | H16: =Staffing!G3 -> 13000 | I16: =Staffing!H3 -> 13000 | K16: =Staffing!J3 -> 13000 | L16: =Staffing!K3 -> 13000 | M16: =Staffing!L3 -> 13000 | O16: =Staffing!N3 -> 13000 | P16: =Staffing!O3 -> 13000 | Q16: =Staffing!P3 -> 13000 | S16: =SUM(C16:Q16) -> 156000
A17: 1099 Staff | C17: =Staffing!B9 -> 1000 | D17: =Staffing!C9 -> 1000 | E17: =Staffing!D9 -> 1000 | G17: =Staffing!F9 -> 1000 | H17: =Staffing!G9 -> 1000 | I17: =Staffing!H9 -> 1000 | K17: =Staffing!J9 -> 1000 | L17: =Staffing!K9 -> 1000 | M17: =Staffing!L9 -> 1000 | O17: =Staffing!N9 -> 1000 | P17: =Staffing!O9 -> 1000 | Q17: =Staffing!P9 -> 1000 | S17: =SUM(C17:Q17) -> 12000
A18: Payroll Taxes | C18: =Staffing!B14 -> 1300 | D18: =Staffing!C14 -> 1300 | E18: =Staffing!D14 -> 1300 | G18: =Staffing!F14 -> 1300 | H18: =Staffing!G14 -> 1300 | I18: =Staffing!H14 -> 1300 | K18: =Staffing!J14 -> 1300 | L18: =Staffing!K14 -> 1300 | M18: =Staffing!L14 -> 1300 | O18: =Staffing!N14 -> 1300 | P18: =Staffing!O14 -> 1300 | Q18: =Staffing!P14 -> 1300 | S18: =SUM(C18:Q18) -> 15600
A19: Benefits | C19: =Staffing!B16 -> 750 | D19: =Staffing!C16 -> 750 | E19: =Staffing!D16 -> 750 | G19: =Staffing!F16 -> 750 | H19: =Staffing!G16 -> 750 | I19: =Staffing!H16 -> 750 | K19: =Staffing!J16 -> 750 | L19: =Staffing!K16 -> 750 | M19: =Staffing!L16 -> 750 | O19: =Staffing!N16 -> 750 | P19: =Staffing!O16 -> 750 | Q19: =Staffing!P16 -> 750 | S19: =SUM(C19:Q19) -> 9000
A21: Office Operations | C21: =SUM(C22:C25) -> 769 | D21: =SUM(D22:D25) -> 769 | E21: =SUM(E22:E25) -> 769 | G21: =SUM(G22:G25) -> 769 | H21: =SUM(H22:H25) -> 769 | I21: =SUM(I22:I25) -> 769 | K21: =SUM(K22:K25) -> 769 | L21: =SUM(L22:L25) -> 769 | M21: =SUM(M22:M25) -> 769 | O21: =SUM(O22:O25) -> 769 | P21: =SUM(P22:P25) -> 769 | Q21: =SUM(Q22:Q25) -> 769 | S21: =SUM(C21:Q21) -> 9228
A22: Office Services | C22: ='Misc Expenses'!B3 -> 650 | D22: ='Misc Expenses'!C3 -> 650 | E22: ='Misc Expenses'!D3 -> 650 | G22: ='Misc Expenses'!F3 -> 650 | H22: ='Misc Expenses'!G3 -> 650 | I22: ='Misc Expenses'!H3 -> 650 | K22: ='Misc Expenses'!J3 -> 650 | L22: ='Misc Expenses'!K3 -> 650 | M22: ='Misc Expenses'!L3 -> 650 | O22: ='Misc Expenses'!N3 -> 650 | P22: ='Misc Expenses'!O3 -> 650 | Q22: ='Misc Expenses'!P3 -> 650 | S22: =SUM(C22:Q22) -> 7800
A23: Subscription Services | C23: ='Misc Expenses'!B14 -> 59 | D23: ='Misc Expenses'!C14 -> 59 | E23: ='Misc Expenses'!D14 -> 59 | G23: ='Misc Expenses'!F14 -> 59 | H23: ='Misc Expenses'!G14 -> 59 | I23: ='Misc Expenses'!H14 -> 59 | K23: ='Misc Expenses'!J14 -> 59 | L23: ='Misc Expenses'!K14 -> 59 | M23: ='Misc Expenses'!L14 -> 59 | O23: ='Misc Expenses'!N14 -> 59 | P23: ='Misc Expenses'!O14 -> 59 | Q23: ='Misc Expenses'!P14 -> 59 | S23: =SUM(C23:Q23) -> 708
A24: Meals and Entertainment
A25: Miscellaneous | C25: ='Misc Expenses'!B28 -> 60 | D25: ='Misc Expenses'!C28 -> 60 | E25: ='Misc Expenses'!D28 -> 60 | G25: ='Misc Expenses'!F28 -> 60 | H25: ='Misc Expenses'!G28 -> 60 | I25: ='Misc Expenses'!H28 -> 60 | K25: ='Misc Expenses'!J28 -> 60 | L25: ='Misc Expenses'!K28 -> 60 | M25: ='Misc Expenses'!L28 -> 60 | O25: ='Misc Expenses'!N28 -> 60 | P25: ='Misc Expenses'!O28 -> 60 | Q25: ='Misc Expenses'!P28 -> 60 | S25: =SUM(C25:Q25) -> 720
A27: Total Operating Expenses | C27: =C8+C10+C15+C21 -> 23989 | D27: =D8+D10+D15+D21 -> 23989 | E27: =E8+E10+E15+E21 -> 23989 | G27: =G8+G10+G15+G21 -> 23989 | H27: =H8+H10+H15+H21 -> 23989 | I27: =I8+I10+I15+I21 -> 23989 | K27: =K8+K10+K15+K21 -> 23989 | L27: =L8+L10+L15+L21 -> 23989 | M27: =M8+M10+M15+M21 -> 23989 | O27: =O8+O10+O15+O21 -> 23989 | P27: =P8+P10+P15+P21 -> 23989 | Q27: =Q8+Q10+Q15+Q21 -> 23989 | S27: =SUM(C27:Q27) -> 287868
A29: Net Operating Income | C29: =C3-C27 -> 796 | D29: =D3-D27 -> 796 | E29: =E3-E27 -> 796 | G29: =G3-G27 -> 796 | H29: =H3-H27 -> 796 | I29: =I3-I27 -> 796 | K29: =K3-K27 -> 796 | L29: =L3-L27 -> 796 | M29: =M3-M27 -> 796 | O29: =O3-O27 -> 796 | P29: =P3-P27 -> 796 | Q29: =Q3-Q27 -> 796 | S29: =SUM(C29:Q29) -> 9552

Sheet Revenue
A1: Revenue | C1: Jan | D1: Feb | E1: Mar | G1: Apr | H1: May | I1: Jun | K1: Jul | L1: Aug | M1: Sep | O1: Oct | P1: Nov | Q1: Dec | S1: Total
A3: Credit Card Revenue | C3: =C4-C5-C6-C7 -> 23250 | D3: =D4-D5-D6-D7 -> 23250 | E3: =E4-E5-E6-E7 -> 23250 | G3: =G4-G5-G6-G7 -> 23250 | H3: =H4-H5-H6-H7 -> 23250 | I3: =I4-I5-I6-I7 -> 23250 | K3: =K4-K5-K6-K7 -> 23250 | L3: =L4-L5-L6-L7 -> 23250 | M3: =M4-M5-M6-M7 -> 23250 | O3: =O4-O5-O6-O7 -> 23250 | P3: =P4-P5-P6-P7 -> 23250 | Q3: =Q4-Q5-Q6-Q7 -> 23250 | S3: =SUM(C3:R3) -> 279000
A4: Income (Credits) | C4: 25000 | D4: 25000 | E4: 25000 | G4: 25000 | H4: 25000 | I4: 25000 | K4: 25000 | L4: 25000 | M4: 25000 | O4: 25000 | P4: 25000 | Q4: 25000
A5: Refunds | B5: 0.03 | C5: =C4*$B$5 -> 750 | D5: =D4*$B$5 -> 750 | E5: =E4*$B$5 -> 750 | G5: =G4*$B$5 -> 750 | H5: =H4*$B$5 -> 750 | I5: =I4*$B$5 -> 750 | K5: =K4*$B$5 -> 750 | L5: =L4*$B$5 -> 750 | M5: =M4*$B$5 -> 750 | O5: =O4*$B$5 -> 750 | P5: =P4*$B$5 -> 750 | Q5: =Q4*$B$5 -> 750
A6: Chargebacks | B6: 0.01 | C6: =C4*$B$6 -> 250 | D6: =D4*$B$6 -> 250 | E6: =E4*$B$6 -> 250 | G6: =G4*$B$6 -> 250 | H6: =H4*$B$6 -> 250 | I6: =I4*$B$6 -> 250 | K6: =K4*$B$6 -> 250 | L6: =L4*$B$6 -> 250 | M6: =M4*$B$6 -> 250 | O6: =O4*$B$6 -> 250 | P6: =P4*$B$6 -> 250 | Q6: =Q4*$B$6 -> 250
A7: Processing Fees | B7: 0.03 | C7: =$B$7*C4 -> 750 | D7: =$B$7*D4 -> 750 | E7: =$B$7*E4 -> 750 | G7: =$B$7*G4 -> 750 | H7: =$B$7*H4 -> 750 | I7: =$B$7*I4 -> 750 | K7: =$B$7*K4 -> 750 | L7: =$B$7*L4 -> 750 | M7: =$B$7*M4 -> 750 | O7: =$B$7*O4 -> 750 | P7: =$B$7*P4 -> 750 | Q7: =$B$7*Q4 -> 750
A9: Checks Received | C9: =C10-C11 -> 1485 | D9: =D10-D11 -> 1485 | E9: =E10-E11 -> 1485 | G9: =G10-G11 -> 1485 | H9: =H10-H11 -> 1485 | I9: =I10-I11 -> 1485 | K9: =K10-K11 -> 1485 | L9: =L10-L11 -> 1485 | M9: =M10-M11 -> 1485 | O9: =O10-O11 -> 1485 | P9: =P10-P11 -> 1485 | Q9: =Q10-Q11 -> 1485 | S9: =SUM(C9:R9) -> 17820
A10: Total of Checks | C10: 1500 | D10: 1500 | E10: 1500 | G10: 1500 | H10: 1500 | I10: 1500 | K10: 1500 | L10: 1500 | M10: 1500 | O10: 1500 | P10: 1500 | Q10: 1500
A11: Refunds | B11: 0.01 | C11: =C10*$B$11 -> 15 | D11: =D10*$B$11 -> 15 | E11: =E10*$B$11 -> 15 | G11: =G10*$B$11 -> 15 | H11: =H10*$B$11 -> 15 | I11: =I10*$B$11 -> 15 | K11: =K10*$B$11 -> 15 | L11: =L10*$B$11 -> 15 | M11: =M10*$B$11 -> 15 | O11: =O10*$B$11 -> 15 | P11: =P10*$B$11 -> 15 | Q11: =Q10*$B$11 -> 15
A13: Other Sources | C13: =SUM(C14) -> 50 | D13: =SUM(D14) -> 50 | E13: =SUM(E14) -> 50 | G13: =SUM(G14) -> 50 | H13: =SUM(H14) -> 50 | I13: =SUM(I14) -> 50 | K13: =SUM(K14) -> 50 | L13: =SUM(L14) -> 50 | M13: =SUM(M14) -> 50 | O13: =SUM(O14) -> 50 | P13: =SUM(P14) -> 50 | Q13: =SUM(Q14) -> 50 | S13: =SUM(C13:R13) -> 600
A14: Misc Sources of Revenue | C14: 50 | D14: 50 | E14: 50 | G14: 50 | H14: 50 | I14: 50 | K14: 50 | L14: 50 | M14: 50 | O14: 50 | P14: 50 | Q14: 50

Sheet COGS
A1: COGS | B1: Jan | C1: Feb | D1: Mar | F1: Apr | G1: May | H1: Jun | J1: Jul | K1: Aug | L1: Sep | N1: Oct | O1: Nov | P1: Dec | R1: Total
A3: Direct Costs | B3: =B4*B5 -> 2000 | C3: =C4*C5 -> 2000 | D3: =D4*D5 -> 2000 | F3: =F4*F5 -> 2000 | G3: =G4*G5 -> 2000 | H3: =H4*H5 -> 2000 | J3: =J4*J5 -> 2000 | K3: =K4*K5 -> 2000 | L3: =L4*L5 -> 2000 | N3: =N4*N5 -> 2000 | O3: =O4*O5 -> 2000 | P3: =P4*P5 -> 2000 | R3: =SUM(B3:Q3) -> 24000
A4: Unit Cost | B4: 1 | C4: 1 | D4: 1 | F4: 1 | G4: 1 | H4: 1 | J4: 1 | K4: 1 | L4: 1 | N4: 1 | O4: 1 | P4: 1
A5: Units Sold | B5: 2000 | C5: 2000 | D5: 2000 | F5: 2000 | G5: 2000 | H5: 2000 | J5: 2000 | K5: 2000 | L5: 2000 | N5: 2000 | O5: 2000 | P5: 2000
A7: Variable Costs | B7: =SUM(B8:B12) -> 4050 | C7: =SUM(C8:C12) -> 4050 | D7: =SUM(D8:D12) -> 4050 | F7: =SUM(F8:F12) -> 4050 | G7: =SUM(G8:G12) -> 4050 | H7: =SUM(H8:H12) -> 4050 | J7: =SUM(J8:J12) -> 4050 | K7: =SUM(K8:K12) -> 4050 | L7: =SUM(L8:L12) -> 4050 | N7: =SUM(N8:N12) -> 4050 | O7: =SUM(O8:O12) -> 4050 | P7: =SUM(P8:P12) -> 4050 | R7: =SUM(B7:P7) -> 48600
A8: Facility (Rent, Mortgage, Taxes) | B8: 1000 | C8: 1000 | D8: 1000 | F8: 1000 | G8: 1000 | H8: 1000 | J8: 1000 | K8: 1000 | L8: 1000 | N8: 1000 | O8: 1000 | P8: 1000
A9: Salaries of Maintenance Personnel | B9: 800 | C9: 800 | D9: 800 | F9: 800 | G9: 800 | H9: 800 | J9: 800 | K9: 800 | L9: 800 | N9: 800 | O9: 800 | P9: 800
A10: Salaries of Manufacturing Managers | B10: 1500 | C10: 1500 | D10: 1500 | F10: 1500 | G10: 1500 | H10: 1500 | J10: 1500 | K10: 1500 | L10: 1500 | N10: 1500 | O10: 1500 | P10: 1500
A11: Supplies for Production Facility | B11: 500 | C11: 500 | D11: 500 | F11: 500 | G11: 500 | H11: 500 | J11: 500 | K11: 500 | L11: 500 | N11: 500 | O11: 500 | P11: 500
A12: Utilities for Production Facility | B12: 250 | C12: 250 | D12: 250 | F12: 250 | G12: 250 | H12: 250 | J12: 250 | K12: 250 | L12: 250 | N12: 250 | O12: 250 | P12: 250
A15: Total COGS | B15: =SUM(B3,B7) -> 6050 | C15: =SUM(C3,C7) -> 6050 | D15: =SUM(D3,D7) -> 6050 | F15: =SUM(F3,F7) -> 6050 | G15: =SUM(G3,G7) -> 6050 | H15: =SUM(H3,H7) -> 6050 | J15: =SUM(J3,J7) -> 6050 | K15: =SUM(K3,K7) -> 6050 | L15: =SUM(L3,L7) -> 6050 | N15: =SUM(N3,N7) -> 6050 | O15: =SUM(O3,O7) -> 6050 | P15: =SUM(P3,P7) -> 6050 | R15: =SUM(B15:P15) -> 72600

Sheet Marketing
A1: Marketing | B1: Jan | C1: Feb | D1: Mar | F1: Apr | G1: May | H1: Jun | J1: Jul | K1: Aug | L1: Sep | N1: Oct | O1: Nov | P1: Dec | R1: Total | S1: Total
A3: Online Channels | B3: =SUM(B4:B5) -> 1000 | C3: =SUM(C4:C5) -> 1000 | D3: =SUM(D4:D5) -> 1000 | F3: =SUM(F4:F5) -> 1000 | G3: =SUM(G4:G5) -> 1000 | H3: =SUM(H4:H5) -> 1000 | J3: =SUM(J4:J5) -> 1000 | K3: =SUM(K4:K5) -> 1000 | L3: =SUM(L4:L5) -> 1000 | N3: =SUM(N4:N5) -> 1000 | O3: =SUM(O4:O5) -> 1000 | P3: =SUM(P4:P5) -> 1000
A4: Google Adwords | B4: 500 | C4: 500 | D4: 500 | F4: 500 | G4: 500 | H4: 500 | J4: 500 | K4: 500 | L4: 500 | N4: 500 | O4: 500 | P4: 500
A5: Facebook Ads | B5: 500 | C5: 500 | D5: 500 | F5: 500 | G5: 500 | H5: 500 | J5: 500 | K5: 500 | L5: 500 | N5: 500 | O5: 500 | P5: 500 | S5: 204660
A7: Offline Channels | B7: =SUM(B8:B9) -> 110 | C7: =SUM(C8:C9) -> 110 | D7: =SUM(D8:D9) -> 110 | F7: =SUM(F8:F9) -> 110 | G7: =SUM(G8:G9) -> 110 | H7: =SUM(H8:H9) -> 110 | J7: =SUM(J8:J9) -> 110 | K7: =SUM(K8:K9) -> 110 | L7: =SUM(L8:L9) -> 110 | N7: =SUM(N8:N9) -> 110 | O7: =SUM(O8:O9) -> 110 | P7: =SUM(P8:P9) -> 110
A8: Referral Fees | B8: 100 | C8: 100 | D8: 100 | F8: 100 | G8: 100 | H8: 100 | J8: 100 | K8: 100 | L8: 100 | N8: 100 | O8: 100 | P8: 100
A9: Print Ads | B9: 10 | C9: 10 | D9: 10 | F9: 10 | G9: 10 | H9: 10 | J9: 10 | K9: 10 | L9: 10 | N9: 10 | O9: 10 | P9: 10
A10: Trade Shows | B10: 100 | C10: 100 | D10: 100 | F10: 100 | G10: 100 | H10: 100 | J10: 100 | K10: 100 | L10: 100 | N10: 100 | O10: 100 | P10: 100
A12: Other Marketing Expenses | B12: =SUM(B13) -> 10 | C12: =SUM(C13) -> 10 | D12: =SUM(D13) -> 10 | F12: =SUM(F13) -> 10 | G12: =SUM(G13) -> 10 | H12: =SUM(H13) -> 10 | J12: =SUM(J13) -> 10 | K12: =SUM(K13) -> 10 | L12: =SUM(L13) -> 10 | N12: =SUM(N13) -> 10 | O12: =SUM(O13) -> 10 | P12: =SUM(P13) -> 10
A13: Anything | B13: 10 | C13: 10 | D13: 10 | F13: 10 | G13: 10 | H13: 10 | J13: 10 | K13: 10 | L13: 10 | N13: 10 | O13: 10 | P13: 10
A15: Total Marketing Costs | B15: =B3+B7+B12 -> 1120 | C15: =C3+C7+C12 -> 1120 | D15: =D3+D7+D12 -> 1120 | F15: =F3+F7+F12 -> 1120 | G15: =G3+G7+G12 -> 1120 | H15: =H3+H7+H12 -> 1120 | J15: =J3+J7+J12 -> 1120 | K15: =K3+K7+K12 -> 1120 | L15: =L3+L7+L12 -> 1120 | N15: =N3+N7+N12 -> 1120 | O15: =O3+O7+O12 -> 1120 | P15: =P3+P7+P12 -> 1120

Sheet Staffing
A1: Staffing | B1: Jan | C1: Feb | D1: Mar | F1: Apr | G1: May | H1: Jun | J1: Jul | K1: Aug | L1: Sep | N1: Oct | O1: Nov | P1: Dec | R1: Total | S1: Total
A3: W2 Staff | B3: =SUM(B4:B7) -> 13000 | C3: =SUM(C4:C7) -> 13000 | D3: =SUM(D4:D7) -> 13000 | F3: =SUM(F4:F7) -> 13000 | G3: =SUM(G4:G7) -> 13000 | H3: =SUM(H4:H7) -> 13000 | J3: =SUM(J4:J7) -> 13000 | K3: =SUM(K4:K7) -> 13000 | L3: =SUM(L4:L7) -> 13000 | N3: =SUM(N4:N7) -> 13000 | O3: =SUM(O4:O7) -> 13000 | P3: =SUM(P4:P7) -> 13000
A4: The CEO | B4: 5000 | C4: 5000 | D4: 5000 | F4: 5000 | G4: 5000 | H4: 5000 | J4: 5000 | K4: 5000 | L4: 5000 | N4: 5000 | O4: 5000 | P4: 5000
A5: Marketing Gal | B5: 4000 | C5: 4000 | D5: 4000 | F5: 4000 | G5: 4000 | H5: 4000 | J5: 4000 | K5: 4000 | L5: 4000 | N5: 4000 | O5: 4000 | P5: 4000 | S5: 204660
A6: Developer Dude | B6: 4000 | C6: 4000 | D6: 4000 | F6: 4000 | G6: 4000 | H6: 4000 | J6: 4000 | K6: 4000 | L6: 4000 | N6: 4000 | O6: 4000 | P6: 4000 | S6: 191412
A9: 1099 Staff | B9: =SUM(B10:B11) -> 1000 | C9: =SUM(C10:C11) -> 1000 | D9: =SUM(D10:D11) -> 1000 | F9: =SUM(F10:F11) -> 1000 | G9: =SUM(G10:G11) -> 1000 | H9: =SUM(H10:H11) -> 1000 | J9: =SUM(J10:J11) -> 1000 | K9: =SUM(K10:K11) -> 1000 | L9: =SUM(L10:L11) -> 1000 | N9: =SUM(N10:N11) -> 1000 | O9: =SUM(O10:O11) -> 1000 | P9: =SUM(P10:P11) -> 1000
A10: Web Designer | B10: 1000 | C10: 1000 | D10: 1000 | F10: 1000 | G10: 1000 | H10: 1000 | J10: 1000 | K10: 1000 | L10: 1000 | N10: 1000 | O10: 1000 | P10: 1000
A14: Payroll Taxes | B14: =B3*0.1 -> 1300 | C14: =C3*0.1 -> 1300 | D14: =D3*0.1 -> 1300 | F14: =F3*0.1 -> 1300 | G14: =G3*0.1 -> 1300 | H14: =H3*0.1 -> 1300 | J14: =J3*0.1 -> 1300 | K14: =K3*0.1 -> 1300 | L14: =L3*0.1 -> 1300 | N14: =N3*0.1 -> 1300 | O14: =O3*0.1 -> 1300 | P14: =P3*0.1 -> 1300
A16: Benefits | B16: =SUM(B17:B19) -> 750 | C16: =SUM(C17:C19) -> 750 | D16: =SUM(D17:D19) -> 750 | F16: =SUM(F17:F19) -> 750 | G16: =SUM(G17:G19) -> 750 | H16: =SUM(H17:H19) -> 750 | J16: =SUM(J17:J19) -> 750 | K16: =SUM(K17:K19) -> 750 | L16: =SUM(L17:L19) -> 750 | N16: =SUM(N17:N19) -> 750 | O16: =SUM(O17:O19) -> 750 | P16: =SUM(P17:P19) -> 750
A17: Healthcare Provider | B17: 750 | C17: 750 | D17: 750 | F17: 750 | G17: 750 | H17: 750 | J17: 750 | K17: 750 | L17: 750 | N17: 750 | O17: 750 | P17: 750
A20: Total Staffing Costs | B20: =B3+B9+B14+B16 -> 16050 | C20: =C3+C9+C14+C16 -> 16050 | D20: =D3+D9+D14+D16 -> 16050 | F20: =F3+F9+F14+F16 -> 16050 | G20: =G3+G9+G14+G16 -> 16050 | H20: =H3+H9+H14+H16 -> 16050 | J20: =J3+J9+J14+J16 -> 16050 | K20: =K3+K9+K14+K16 -> 16050 | L20: =L3+L9+L14+L16 -> 16050 | N20: =N3+N9+N14+N16 -> 16050 | O20: =O3+O9+O14+O16 -> 16050 | P20: =P3+P9+P14+P16 -> 16050

Sheet Misc Expenses
A1: Misc Expenses | B1: Jan | C1: Feb | D1: Mar | F1: Apr | G1: May | H1: Jun | J1: Jul | K1: Aug | L1: Sep | N1: Oct | O1: Nov | P1: Dec | R1: Total
A3: Office Services | B3: =SUM(B4:B13) -> 650 | C3: =SUM(C4:C13) -> 650 | D3: =SUM(D4:D13) -> 650 | F3: =SUM(F4:F13) -> 650 | G3: =SUM(G4:G13) -> 650 | H3: =SUM(H4:H13) -> 650 | J3: =SUM(J4:J13) -> 650 | K3: =SUM(K4:K13) -> 650 | L3: =SUM(L4:L13) -> 650 | N3: =SUM(N4:N13) -> 650 | O3: =SUM(O4:O13) -> 650 | P3: =SUM(P4:P13) -> 650
A4: Office Rent | B4: 500 | C4: 500 | D4: 500 | F4: 500 | G4: 500 | H4: 500 | J4: 500 | K4: 500 | L4: 500 | N4: 500 | O4: 500 | P4: 500
A5: Internet Connectivity | B5: 75 | C5: 75 | D5: 75 | F5: 75 | G5: 75 | H5: 75 | J5: 75 | K5: 75 | L5: 75 | N5: 75 | O5: 75 | P5: 75
A6: Hosting Bill | B6: 50 | C6: 50 | D6: 50 | F6: 50 | G6: 50 | H6: 50 | J6: 50 | K6: 50 | L6: 50 | N6: 50 | O6: 50 | P6: 50
A7: Cleaning Service | B7: 25 | C7: 25 | D7: 25 | F7: 25 | G7: 25 | H7: 25 | J7: 25 | K7: 25 | L7: 25 | N7: 25 | O7: 25 | P7: 25
A14: Subscription Services | B14: =SUM(B15:B27) -> 59 | C14: =SUM(C15:C27) -> 59 | D14: =SUM(D15:D27) -> 59 | F14: =SUM(F15:F27) -> 59 | G14: =SUM(G15:G27) -> 59 | H14: =SUM(H15:H27) -> 59 | J14: =SUM(J15:J27) -> 59 | K14: =SUM(K15:K27) -> 59 | L14: =SUM(L15:L27) -> 59 | N14: =SUM(N15:N27) -> 59 | O14: =SUM(O15:O27) -> 59 | P14: =SUM(P15:P27) -> 59
A15: Startups Unlimited Subscription | B15: 29 | C15: 29 | D15: 29 | F15: 29 | G15: 29 | H15: 29 | J15: 29 | K15: 29 | L15: 29 | N15: 29 | O15: 29 | P15: 29
A16: Payroll Service | B16: 30 | C16: 30 | D16: 30 | F16: 30 | G16: 30 | H16: 30 | J16: 30 | K16: 30 | L16: 30 | N16: 30 | O16: 30 | P16: 30
A28: Meals and Entertainment | B28: =SUM(B29:B35) -> 60 | C28: =SUM(C29:C35) -> 60 | D28: =SUM(D29:D35) -> 60 | F28: =SUM(F29:F35) -> 60 | G28: =SUM(G29:G35) -> 60 | H28: =SUM(H29:H35) -> 60 | J28: =SUM(J29:J35) -> 60 | K28: =SUM(K29:K35) -> 60 | L28: =SUM(L29:L35) -> 60 | N28: =SUM(N29:N35) -> 60 | O28: =SUM(O29:O35) -> 60 | P28: =SUM(P29:P35) -> 60
A29: Team Dinner | B29: 45 | C29: 45 | D29: 45 | F29: 45 | G29: 45 | H29: 45 | J29: 45 | K29: 45 | L29: 45 | N29: 45 | O29: 45 | P29: 45
A30: Placeholder Value | B30: 15 | C30: 15 | D30: 15 | F30: 15 | G30: 15 | H30: 15 | J30: 15 | K30: 15 | L30: 15 | N30: 15 | O30: 15 | P30: 15
A36: Other | B36: =SUM(B37:B61) -> 25 | C36: =SUM(C37:C61) -> 25 | D36: =SUM(D37:D61) -> 25 | F36: =SUM(F37:F61) -> 25 | G36: =SUM(G37:G61) -> 25 | H36: =SUM(H37:H61) -> 25 | J36: =SUM(J37:J61) -> 25 | K36: =SUM(K37:K61) -> 25 | L36: =SUM(L37:L61) -> 25 | N36: =SUM(N37:N61) -> 25 | O36: =SUM(O37:O61) -> 25 | P36: =SUM(P37:P61) -> 25
A37: Travel | B37: 20 | C37: 20 | D37: 20 | F37: 20 | G37: 20 | H37: 20 | J37: 20 | K37: 20 | L37: 20 | N37: 20 | O37: 20 | P37: 20
A38: Cost | B38: 5 | C38: 5 | D38: 5 | F38: 5 | G38: 5 | H38: 5 | J38: 5 | K38: 5 | L38: 5 | N38: 5 | O38: 5 | P38: 5

Sheet Assumptions
A1: Assumptions | B1: Jan | C1: Feb | D1: Mar | F1: Apr | G1: May | H1: Jun | J1: Jul | K1: Aug | L1: Sep | N1: Oct | O1: Nov | P1: Dec
A2: Yellow = Input Box
A3: Customer Acquisition Costs (CAC)
A4: Budget | B4: 1000 | C4: 1000 | D4: 1000 | F4: 1000 | G4: 1000 | H4: 1000 | J4: 1000 | K4: 1000 | L4: 1000 | N4: 1000 | O4: 1000 | P4: 1000
A5: Cost Per Visitor | B5: 0.5 | C5: 0.5 | D5: 0.5 | F5: 0.5 | G5: 0.5 | H5: 0.5 | J5: 0.5 | K5: 0.5 | L5: 0.5 | N5: 0.5 | O5: 0.5 | P5: 0.5
A6: Total Paid Visitors | B6: =B4/B5 -> 2000 | C6: =C4/C5 -> 2000 | D6: =D4/D5 -> 2000 | F6: =F4/F5 -> 2000 | G6: =G4/G5 -> 2000 | H6: =H4/H5 -> 2000 | J6: =J4/J5 -> 2000 | K6: =K4/K5 -> 2000 | L6: =L4/L5 -> 2000 | N6: =N4/N5 -> 2000 | O6: =O4/O5 -> 2000 | P6: =P4/P5 -> 2000
A7: Total Organic Visitors | B7: 1000 | C7: 1000 | D7: 1000 | F7: 1000 | G7: 1000 | H7: 1000 | J7: 1000 | K7: 1000 | L7: 1000 | N7: 1000 | O7: 1000 | P7: 1000
A8: Total ALL Visitors | B8: =B6+B7 -> 3000 | C8: =C6+C7 -> 3000 | D8: =D6+D7 -> 3000 | F8: =F6+F7 -> 3000 | G8: =G6+G7 -> 3000 | H8: =H6+H7 -> 3000 | J8: =J6+J7 -> 3000 | K8: =K6+K7 -> 3000 | L8: =L6+L7 -> 3000 | N8: =N6+N7 -> 3000 | O8: =O6+O7 -> 3000 | P8: =P6+P7 -> 3000
A10: Conversion Rate
A11: Conversion to Paid Customers | B11: 0.03 | C11: 0.03 | D11: 0.03 | F11: 0.03 | G11: 0.03 | H11: 0.03 | J11: 0.03 | K11: 0.03 | L11: 0.03 | N11: 0.03 | O11: 0.03 | P11: 0.03
A12: Total Number of Paid Customers | B12: =B8*B11 -> 90 | C12: =C8*C11 -> 90 | D12: =D8*D11 -> 90 | F12: =F8*F11 -> 90 | G12: =G8*G11 -> 90 | H12: =H8*H11 -> 90 | J12: =J8*J11 -> 90 | K12: =K8*K11 -> 90 | L12: =L8*L11 -> 90 | N12: =N8*N11 -> 90 | O12: =O8*O11 -> 90 | P12: =P8*P11 -> 90
A14: Order Value (New Revenue)
A15: Average New Order Value | B15: 50 | C15: 50 | D15: 50 | F15: 50 | G15: 50 | H15: 50 | J15: 50 | K15: 50 | L15: 50 | N15: 50 | O15: 50 | P15: 50
A16: Total New Revenue | B16: =B12*B15 -> 4500 | C16: =C12*C15 -> 4500 | D16: =D12*D15 -> 4500 | F16: =F12*F15 -> 4500 | G16: =G12*G15 -> 4500 | H16: =H12*H15 -> 4500 | J16: =J12*J15 -> 4500 | K16: =K12*K15 -> 4500 | L16: =L12*L15 -> 4500 | N16: =N12*N15 -> 4500 | O16: =O12*O15 -> 4500 | P16: =P12*P15 -> 4500
A18: Recurring Revenue
A19: Churn Rate | B19: 0.25 | C19: 0.25 | D19: 0.25 | F19: 0.25 | G19: 0.25 | H19: 0.25 | J19: 0.25 | K19: 0.25 | L19: 0.25 | N19: 0.25 | O19: 0.25 | P19: 0.25
A20: Total Recurring Revenue | B20: 0 | C20: =((B22*(1-C19))) -> 3375 | D20: =(C22)*(1-D19) -> 5906.25 | F20: =(D22)*(1-F19) -> 7804.6875 | G20: =(F22)*(1-G19) -> 9228.5156 | H20: =(G22)*(1-H19) -> 10296.387 | J20: =(H22)*(1-J19) -> 11097.29 | K20: =(J22)*(1-K19) -> 11697.968 | L20: =(K22)*(1-L19) -> 12148.476 | N20: =(L22)*(1-N19) -> 12486.357 | O20: =(N22)*(1-O19) -> 12739.768 | P20: =(O22)*(1-P19) -> 12929.826
A22: Total Revenue | B22: =B16+B20 -> 4500 | C22: =C16+C20 -> 7875 | D22: =D16+D20 -> 10406.25 | F22: =F16+F20 -> 12304.688 | G22: =G20+G16 -> 13728.516 | H22: =H16+H20 -> 14796.387 | J22: =J16+J20 -> 15597.29 | K22: =K20+K16 -> 16197.968 | L22: =L16+L20 -> 16648.476 | N22: =N16+N20 -> 16986.357 | O22: =O20+O16 -> 17239.768 | P22: =P16+P20 -> 17429.826
A24: Cost of Goods Sold (COGS)
A25: Credit Card Processing @ 3% | B25: =B22*3% -> 135 | C25: =C22*3% -> 236.25 | D25: =D22*3% -> 312.1875 | F25: =F22*3% -> 369.14062 | G25: =G22*3% -> 411.85547 | H25: =H22*3% -> 443.8916 | J25: =J22*3% -> 467.9187 | K25: =K22*3% -> 485.93903 | L25: =L22*3% -> 499.45427 | N25: =N16*3% -> 135 | O25: =O16*3% -> 135 | P25: =P16*3% -> 135
A26: Product Unit Cost | B26: 25 | C26: 25 | D26: 25 | F26: 25 | G26: 25 | H26: 25 | J26: 25 | K26: 25 | L26: 25 | N26: 25 | O26: 25 | P26: 25
A27: Total Product Cost | B27: =B12*B26 -> 2250 | C27: =C12*C26 -> 2250 | D27: =D12*D26 -> 2250 | F27: =F12*F26 -> 2250 | G27: =G12*G26 -> 2250 | H27: =H12*H26 -> 2250 | J27: =J12*J26 -> 2250 | K27: =K12*K26 -> 2250 | L27: =L12*L26 -> 2250 | N27: =N12*N26 -> 2250 | O27: =O12*O26 -> 2250 | P27: =P12*P26 -> 2250
A28: Variable Cost #1 | B28: 300 | C28: 300 | D28: 300 | F28: 300 | G28: 300 | H28: 300 | J28: 300 | K28: 300 | L28: 300 | N28: 300 | O28: 300 | P28: 300
A29: Variable Cost #2 | B29: 400 | C29: 400 | D29: 400 | F29: 400 | G29: 400 | H29: 400 | J29: 400 | K29: 400 | L29: 400 | N29: 400 | O29: 400 | P29: 400
A30: Total COGS | B30: =B25+B27+B28+B29 -> 3085 | C30: =C25+C27+C28+C29 -> 3186.25 | D30: =D25+D27+D28+D29 -> 3262.1875 | F30: =F25+F27+F28+F29 -> 3319.1406 | G30: =G25+G27+G28+G29 -> 3361.8555 | H30: =H25+H27+H28+H29 -> 3393.8916 | J30: =J25+J27+J28+J29 -> 3417.9187 | K30: =K25+K27+K28+K29 -> 3435.939 | L30: =L25+L27+L28+L29 -> 3449.4543 | N30: =N25+N27+N28+N29 -> 3085 | O30: =O25+O27+O28+O29 -> 3085 | P30: =P25+P27+P28+P29 -> 3085
A32: Gross Margin
A34: Total Customer Revenue | B34: =B16+B20 -> 4500 | C34: =C16+C20 -> 7875 | D34: =D16+D20 -> 10406.25 | F34: =F16+F20 -> 12304.688 | G34: =G16+G20 -> 13728.516 | H34: =H16+H20 -> 14796.387 | J34: =J16+J20 -> 15597.29 | K34: =K16+K20 -> 16197.968 | L34: =L16+L20 -> 16648.476 | N34: =N16+N20 -> 16986.357 | O34: =O16+O20 -> 17239.768 | P34: =P16+P20 -> 17429.826
A35: Marketing (CAC) Costs | B35: =B4 -> 1000 | C35: =C4 -> 1000 | D35: =D4 -> 1000 | F35: =F4 -> 1000 | G35: =G4 -> 1000 | H35: =H4 -> 1000 | J35: =J4 -> 1000 | K35: =K4 -> 1000 | L35: =L4 -> 1000 | N35: =N4 -> 1000 | O35: =O4 -> 1000 | P35: =P4 -> 1000
A36: Cost of Goods Sold | B36: =B30 -> 3085 | C36: =C30 -> 3186.25 | D36: =D30 -> 3262.1875 | F36: =F30 -> 3319.1406 | G36: =G30 -> 3361.8555 | H36: =H30 -> 3393.8916 | J36: =J30 -> 3417.9187 | K36: =K30 -> 3435.939 | L36: =L30 -> 3449.4543 | N36: =N30 -> 3085 | O36: =O30 -> 3085 | P36: =P30 -> 3085
A38: Total Gross Margin | B38: =B34-B35-B36 -> 415 | C38: =C34-C35-C36 -> 3688.75 | D38: =D34-D35-D36 -> 6144.0625 | F38: =F34-F35-F36 -> 7985.5469 | G38: =G34-G35-G36 -> 9366.6602 | H38: =H34-H35-H36 -> 10402.495 | J38: =J34-J35-J36 -> 11179.371 | K38: =K34-K35-K36 -> 11762.029 | L38: =L34-L35-L36 -> 12199.021 | N38: =N34-N35-N36 -> 12901.357 | O38: =O34-O35-O36 -> 13154.768 | P38: =P34-P35-P36 -> 13344.826
